README.md
setup.py
test/test_datasets.py
test/test_meters.py
test/test_transforms.py
torchnet/__init__.py
torchnet/transform.py
torchnet/dataset/__init__.py
torchnet/dataset/batchdataset.py
torchnet/dataset/concatdataset.py
torchnet/dataset/dataset.py
torchnet/dataset/listdataset.py
torchnet/dataset/resampledataset.py
torchnet/dataset/shuffledataset.py
torchnet/dataset/splitdataset.py
torchnet/dataset/tensordataset.py
torchnet/dataset/transformdataset.py
torchnet/engine/__init__.py
torchnet/engine/engine.py
torchnet/logger/__init__.py
torchnet/logger/logger.py
torchnet/logger/meterlogger.py
torchnet/logger/visdomlogger.py
torchnet/meter/__init__.py
torchnet/meter/apmeter.py
torchnet/meter/aucmeter.py
torchnet/meter/averagevaluemeter.py
torchnet/meter/classerrormeter.py
torchnet/meter/confusionmeter.py
torchnet/meter/mapmeter.py
torchnet/meter/meter.py
torchnet/meter/movingaveragevaluemeter.py
torchnet/meter/msemeter.py
torchnet/meter/timemeter.py
torchnet/utils/__init__.py
torchnet/utils/multitaskdataloader.py
torchnet/utils/resultswriter.py
torchnet/utils/table.py
torchnet_sax.egg-info/PKG-INFO
torchnet_sax.egg-info/SOURCES.txt
torchnet_sax.egg-info/dependency_links.txt
torchnet_sax.egg-info/requires.txt
torchnet_sax.egg-info/top_level.txt
torchnet_sax.egg-info/zip-safe